{
  "format_version": 1,
  "release_id": "release-0.1.2-1762344736",
  "target_version": "0.1.2",
  "version_bump": "Patch",
  "started_at": "2025-11-05T12:12:16.062655Z",
  "updated_at": "2025-11-05T12:12:20.206776Z",
  "current_phase": "GitHubRelease",
  "checkpoints": [
    {
      "name": "git_operations_complete",
      "phase": "GitOperations",
      "timestamp": "2025-11-05T12:12:19.517489Z",
      "data": null,
      "rollback_capable": true
    },
    {
      "name": "github_release_created",
      "phase": "GitHubRelease",
      "timestamp": "2025-11-05T12:12:20.206774Z",
      "data": {
        "html_url": "https://github.com/cyrup-ai/kodegen-tools-filesystem/releases/tag/untagged-4c2b2f49e447fe03f9e3",
        "release_id": 259881602
      },
      "rollback_capable": true
    }
  ],
  "version_state": null,
  "git_state": null,
  "github_state": {
    "owner": "cyrup-ai",
    "repo": "kodegen-tools-filesystem",
    "release_id": 259881602,
    "html_url": "https://github.com/cyrup-ai/kodegen-tools-filesystem/releases/tag/untagged-4c2b2f49e447fe03f9e3",
    "draft": true,
    "prerelease": true
  },
  "publish_state": null,
  "errors": [],
  "config": {
    "dry_run_first": true,
    "push_to_remote": true,
    "inter_package_delay_ms": 15000,
    "registry": null,
    "allow_dirty": false,
    "additional_options": {}
  }
}